testpod/__init__.py
testpod/main.py
testpod/main.windows.py
ni_dtots_testpod-0.0.1.dist-info/LICENSE
ni_dtots_testpod-0.0.1.dist-info/METADATA
ni_dtots_testpod-0.0.1.dist-info/WHEEL
ni_dtots_testpod-0.0.1.dist-info/top_level.txt
ni_dtots_testpod-0.0.1.dist-info/RECORD
