Metadata-Version: 2.1
Name: ni-dtots-testpod
Version: 0.0.1
Summary: A testpod
Author-email: Varun Mehra <varun.mehra@ni.com>, Valliappan Meyyappan <valliappan.meyyappan@ni.com>, Abhishek Sharma <abhishek.n.sharma@ni.com>
License: Copyright (c) 2018 The Python Packaging Authority        
Project-URL: Homepage, https://github.com/ni-lti-test-virtualization/dtots2022-testpod-python
Project-URL: Bug Tracker, https://github.com/ni-lti-test-virtualization/dtots2022-testpod-python/issues?q=is%3Aissue+is%3Aopen+sort%3Aupdated-desc
Classifier: Programming Language :: Python :: 3
Classifier: License :: OSI Approved :: MIT License
Classifier: Operating System :: OS Independent
Requires-Python: >=3.7
License-File: LICENSE
